splatviz_network/__init__.py
splatviz_network-0.0.3.dist-info/licenses/LICENSE
splatviz_network-0.0.3.dist-info/METADATA
splatviz_network-0.0.3.dist-info/WHEEL
splatviz_network-0.0.3.dist-info/top_level.txt
splatviz_network-0.0.3.dist-info/RECORD
