Metadata-Version: 2.4
Name: splatviz_network
Version: 0.0.3
Summary: Network connector for splatviz
Home-page: https://github.com/Florian-Barthel/splatviz_network
Author: Florian Barthel
Author-email: florian.tim.barthel@hhi.fraunhofer.de
License: MIT License
Classifier: Development Status :: 3 - Alpha
Classifier: Intended Audience :: Science/Research
Classifier: License :: OSI Approved :: MIT License
Classifier: Operating System :: POSIX :: Linux
Classifier: Operating System :: Microsoft :: Windows
Classifier: Programming Language :: Python
License-File: LICENSE
Requires-Dist: torch
Dynamic: author
Dynamic: author-email
Dynamic: classifier
Dynamic: home-page
Dynamic: license
Dynamic: license-file
Dynamic: requires-dist
Dynamic: summary
